selfdocprint/__init__.py
selfdocprint/_layout_specs.py
selfdocprint/_printer.py
selfdocprint/console.py
selfdocprint/examples/basic_use.py
selfdocprint/selfdocprint.py
selfdocprint-0.2.2.dist-info/LICENSE
selfdocprint-0.2.2.dist-info/METADATA
selfdocprint-0.2.2.dist-info/WHEEL
selfdocprint-0.2.2.dist-info/RECORD
