Metadata-Version: 2.1
Name: selfdocprint
Version: 0.2.2
Summary: A self-documenting, auto-layout print() function.
Home-page: https://github.com/marcelloDC/selfdocprint
License: GPL-3.0-only
Keywords: print,pretty,self-documenting,layout,format
Author: Marcel de Croock
Author-email: marcel.decroock@gmail.com
Requires-Python: >=3.11
Classifier: Development Status :: 4 - Beta
Classifier: Intended Audience :: Developers
Classifier: License :: OSI Approved :: GNU General Public License v3 (GPLv3)
Classifier: Programming Language :: Python :: 3
Classifier: Programming Language :: Python :: 3.11
Classifier: Programming Language :: Python :: 3 :: Only
Classifier: Topic :: Software Development
Project-URL: Repository, https://github.com/marcelloDC/selfdocprint
